setup.py
gaussian_binomial_probability_new/Binomialdistribution.py
gaussian_binomial_probability_new/Gaussiandistribution.py
gaussian_binomial_probability_new/Generaldistribution.py
gaussian_binomial_probability_new/__init__.py
gaussian_binomial_probability_new.egg-info/PKG-INFO
gaussian_binomial_probability_new.egg-info/SOURCES.txt
gaussian_binomial_probability_new.egg-info/dependency_links.txt
gaussian_binomial_probability_new.egg-info/not-zip-safe
gaussian_binomial_probability_new.egg-info/top_level.txt