Metadata-Version: 1.0
Name: gaussian-binomial-probability-new
Version: 0.2
Summary: Gaussian and Binomial distributions
Home-page: UNKNOWN
Author: Adarsh Vinayak
Author-email: UNKNOWN
License: UNKNOWN
Platform: UNKNOWN
